{
  "marketing_stripe": {
    "text": "Tudo em até 6x sem juros | 5% desconto para PIX | SP - Capital Frete Expresso | Use o Cupom: PRIMEIRACOMPRA",
    "link": "/promotion",
    "background": "#393941",
    "color": "#2d2c30"
  },
  "contacts_stripe": {
    "pages": [
      {
        "title": "ENTRAR | CADASTRAR",
        "link": "/pages/sobre-nos"
      }
    ],
    "phone_wpp": false,
    "socials": true
  },
  "categories_list": {
    "featured": [],
    "random": 6,
    "full_width": false
  },
  "search_input": true
}