{
  "meta_title": "PARA la CASA - Décor | Design | Tableware",
  "meta_description": "SHOP on LINE, peças com cuidadosa curadoria, design, tableware e tendências para o décor da sua Casa. Entregamos em todo o Brasil.",
  "sections": [
    {
      "type": "banners-grid",
      "banners": [
        {
          "img": "/img/uploads/e-com-plus-home-capuccino-788-x-518-px-_24_.webp",
          "link": "https://www.paralacasa.com.br/cafe-da-manha",
          "alt": "Nossas apostas para servir o café da manhã com uma coleção com tudo o que precisamos para servir. Para La Casa"
        },
        {
          "img": "/img/uploads/e-com-plus-home-bambu788-x-518-px-18-.jpg",
          "link": "https://www.paralacasa.com.br/tudo-em-bambu/",
          "alt": "Com o DNA brasileiro nossas apostas em bambu para servir e deixar a mesa mais original."
        }
      ]
    },
    {
      "type": "banners-grid",
      "banners": [
        {
          "img": "/img/uploads/e-com-plus-home-prataria-788-x-518-px-24-.jpg",
          "link": "https://www.paralacasa.com.br/prataria",
          "alt": "Nossas escolhas para a prataria para uso diário ou para servir em momentos afetivos."
        },
        {
          "img": "/img/uploads/e-com-plus-home-mix-and-match-bitossi-788-x-518-px-_24_.webp",
          "link": "https://www.paralacasa.com.br/colecao-bitossi-home",
          "alt": "Um mix and match mais que perfeito! Misturar e criar novas possibilidades com as coleções da Bitossi."
        }
      ]
    },
    {
      "type": "collection-shelf",
      "shuffle": false,
      "limit": 12,
      "page": 1,
      "collection_id": null,
      "sort": "news",
      "link": "https://www.paralacasa.com.br/new",
      "title": "New In"
    },
    {
      "type": "banners-grid",
      "banners": [
        {
          "img": "/img/uploads/ecom-plus-home-imagens-527-x-515-px-23-.jpg",
          "link": "https://www.paralacasa.com.br/imagens",
          "alt": "Imagens em pó de mármore com design contemporâneo que complementa o décor e os nossos momentos de conexão espiritual."
        },
        {
          "img": "/img/uploads/ecom-plus-527-x-515-px-home-manta-decor-24-.jpg",
          "link": "https://www.paralacasa.com.br/mantas",
          "alt": "Novas apostas para mantas em cores, estampas e texturas que trazem um ar renovado para o décor."
        },
        {
          "img": "/img/uploads/ecom-plus-527-x-515-bandeja-cafe-da-manha-px-23-.jpg",
          "link": "https://www.paralacasa.com.br/posts/manhas-que-abracam",
          "alt": "Uma bandeja um café, um afeto."
        }
      ]
    },
    {
      "type": "collection-shelf",
      "shuffle": false,
      "limit": 12,
      "page": 1,
      "sort": "news",
      "title": "CURADORIA DA SEMANA",
      "link": "https://www.paralacasa.com.br/destaques",
      "collection_id": "65ce7a8587ab487fbfb9261d:collections:As escolhas da semana:/destaques"
    },
    {
      "type": "banners-grid",
      "banners": [
        {
          "img": "/img/uploads/ecom-plus-527-x-515-home-vaso-dzt-px-23-.jpg",
          "link": "https://www.paralacasa.com.br/vasos/",
          "alt": "Novas escolhas para vasos cheios de poesia para ressignificar o décor"
        },
        {
          "img": "/img/uploads/ecom-plus-527-x-515-home-unque-px-23-.jpg",
          "link": "https://www.paralacasa.com.br/posts/frases-que-bordam-alma-nos-detalhes",
          "alt": "Bordados feitos à mão que nos trazem arte e reflexão."
        },
        {
          "img": "/img/uploads/ecom-plus-527-x-515-home-gift-dzt-px-23-.jpg",
          "link": "https://www.paralacasa.com.br/gifts",
          "alt": "Mais que um marcador de páginas nossos novos objetos marcam nossas histórias com muita memória afetiva. Ótimos para presentear."
        }
      ]
    },
    {
      "type": "collection-shelf",
      "shuffle": false,
      "limit": 12,
      "page": 1,
      "collection_id": "6599d79e2cd6b65959f60cf4:collections:O que nossas clientes têm visto por aqui:/o-que-nossas-clientes-tem-visto-por-aqui",
      "sort": "sales",
      "link": "https://www.paralacasa.com.br/o-que-nossas-clientes-tem-visto-por-aqui",
      "title": "NOSSOS CLIENTES RECOMENDAM"
    },
    {
      "type": "banners-grid",
      "banners": [
        {
          "img": "/img/uploads/e-com-plus-home-eme-black-788-x-518-px-23-.jpg",
          "link": "https://www.paralacasa.com.br/colecao-eme",
          "alt": "EME faqueiros italianos chegam para fazer sucesso em nossas mesas."
        },
        {
          "img": "/img/uploads/e-com-plus-home-mundinho-788-x-518-px-23-.jpg",
          "link": "https://www.paralacasa.com.br/colecao-mundinho",
          "alt": "Feitos à mão, cheios de poesia eles ressignificam o décor"
        }
      ]
    },
    {
      "type": "collection-shelf",
      "shuffle": false,
      "limit": 12,
      "page": 1,
      "collection_id": "638626b273321213f8f92dac:categories:GIFTS:/gifts",
      "sort": "views",
      "link": "https://www.paralacasa.com.br/gifts",
      "title": "GIFTS"
    }
  ]
}