{
  "title": "SHOP BY LOOK ",
  "meta_title": "SHOP BY LOOK ",
  "sections": [
    {
      "type": "extra-page",
      "enabled": true
    },
    {
      "type": "banners-grid",
      "banners": [
        {
          "img": "/img/uploads/cafe-da-manha-colecao-olinda.jpg",
          "link": "https://www.paralacasa.com.br/pages/colecao-olinda",
          "alt": "Mesa de café da manhã elegante com louça Coleção Olinda e detalhes em bambu, Para La Casa"
        },
        {
          "img": "/img/uploads/ecom-plus-olinda-off-white-shop-the-look-527-x-515-px-13-.jpg",
          "link": "https://www.paralacasa.com.br/pages/olinda-off-white-bambu",
          "alt": "Conjunto de mesa Coleção Olinda White: louça branca, jarras e utensílios com bambu, Para La Casa"
        },
        {
          "img": "/img/uploads/colecao-olinda-porcelana-paralacasa-shop.jpg",
          "link": "https://www.paralacasa.com.br/pages/cafe-da-manha-olinda-azul",
          "alt": "Mesa posta elegante Coleção Olinda Azul com louça de porcelana, Para La Casa"
        }
      ]
    },
    {
      "type": "banners-grid",
      "banners": [
        {
          "img": "/img/uploads/jogos-americanos-fibras-bambu-paralacasa-shop.jpg",
          "alt": "Mesa posta elegante com jogos americanos de fibras naturais e talheres com detalhes em bambu, Para La Casa",
          "link": "https://www.paralacasa.com.br/pages/cha-da-tarde"
        },
        {
          "img": "/img/uploads/colecao-cafe-manha-marfim-paralacasa-shop.jpg",
          "link": "https://www.paralacasa.com.br/colecao-marfim",
          "alt": "Mesa de café da manhã elegante Coleção Marfim, com louça e detalhes em vime, Para La Casa"
        },
        {
          "img": "/img/uploads/mesa-posta-azul-intenso-paralacasa-shop.jpg",
          "link": "https://www.paralacasa.com.br/colecao-azul",
          "alt": "Mesa posta elegante com louça azul intenso e detalhes em bambu, Para La Casa"
        }
      ]
    },
    {
      "type": "banners-grid",
      "banners": [
        {
          "img": "/img/uploads/cafe-manha-acrilicos-paralacasa-shop.jpg",
          "link": "https://www.paralacasa.com.br/pages/cafe-da-manha-acrilicos",
          "alt": "Mesa de café da manhã organizada com recipientes de acrílico, Para La Casa"
        },
        {
          "img": "/img/uploads/cafe-da-tarde-lunch-paralacasa-shop.jpg",
          "link": "https://www.paralacasa.com.br/pages/lunch-time",
          "alt": "Mesa de almoço ou café da tarde elegante com vasos de vidro e salada, Para La Casa"
        },
        {
          "img": "/img/uploads/mesa-posta-almoco-paralacasa-shop.jpg",
          "link": "https://www.paralacasa.com.br/pages/almoco-outdoors",
          "alt": "Louça branca e utensílios com detalhes em bambu para mesa posta de almoço, Para La Casa"
        }
      ]
    },
    {
      "type": "banners-grid",
      "banners": [
        {
          "img": "/img/uploads/blue-and-white-paralacasa.jpg",
          "link": "https://www.paralacasa.com.br/pages/blue-and-white",
          "alt": "Decoração de mesa em azul e branco, talheres sofisticados, estilo clássico, Para La Casa"
        },
        {
          "img": "/img/uploads/cafe-manha-luxo-mesa-posta-paralacasa-shop.jpg",
          "link": "https://www.paralacasa.com.br/pages/summer-times",
          "alt": "Mesa posta elegante para café da manhã com flores e utensílios, Para La Casa"
        },
        {
          "img": "/img/uploads/wafles-paralacasa-mesaposta-shop.jpg",
          "link": "https://www.paralacasa.com.br/pages/waflles-no-domingo",
          "alt": "Prato com waffles, talheres e decoração de mesa para café da manhã, Para La Casa"
        }
      ]
    },
    {
      "type": "banners-grid",
      "banners": [
        {
          "img": "/img/uploads/weekend-mesa-posta-paralacasa-luxo-shop.jpg",
          "link": "https://www.paralacasa.com.br/pages/weekend",
          "alt": "Mesa posta elegante para final de semana, com louça verde e talheres sofisticados, Para La Casa"
        },
        {
          "img": "/img/uploads/colecao-marbella-porcelana-paralacasa-shop.jpg",
          "link": "https://www.paralacasa.com.br/pages/tapas-1",
          "alt": "Cerâmicas Coleção Marbella para servir aperitivos em mesa posta, Para La Casa"
        },
        {
          "img": "/img/uploads/colecao-ilheus-ceramica-paralacasa-luxo-shop.jpg",
          "link": "https://www.paralacasa.com.br/pages/ilheus",
          "alt": "Cerâmicas Coleção Ilhéus para mesa posta, design exclusivo, Para La Casa"
        }
      ]
    },
    {
      "type": "banners-grid",
      "banners": [
        {
          "img": "/img/uploads/aromas-difusores-paralacasa.jpg",
          "link": "https://www.paralacasa.com.br/aromas",
          "alt": "Produtos de aromaterapia L'envie Parfums: sabonete líquido e difusor, Para La Casa"
        },
        {
          "img": "/img/uploads/lavabo-decoracao-organizacao-paralacasa-shop.jpg",
          "link": "https://www.paralacasa.com.br/pages/lavabo"
        },
        {
          "img": "/img/uploads/vasos-decoracao-paralacasa-shop.jpg",
          "link": "https://www.paralacasa.com.br/pages/colorfull-pots"
        }
      ]
    },
    {
      "type": "banners-grid",
      "banners": [
        {
          "img": "/img/uploads/bandejas-paralacasa-shopbylook.jpg",
          "link": "https://www.paralacasa.com.br/pages/bandeja-aperitivos",
          "alt": "Bandejas para aperitivos em mesa posta festiva, decoração elegante, Para La Casa"
        },
        {
          "img": "/img/uploads/mesa-posta-paralacasa-shop.jpg",
          "link": "https://www.paralacasa.com.br/pages/tapas",
          "alt": "Mesa posta elegante com utensílios e pratos para tapas, Para La Casa"
        },
        {
          "img": "/img/uploads/tabuas-aperitivos-paralacasa-shop.jpg",
          "link": "https://www.paralacasa.com.br/pages/tabuas-e-aperitivos",
          "alt": "Mesa posta elegante com tábuas de aperitivos e decoração floral, Para La Casa"
        }
      ]
    }
  ],
  "body": "## SHOP by LOOK\n\n\nCompartilhando as produções, apostas e escolhas, aqui o nosso olhar sobre as peças e como usá-las em nossas casas.",
  "meta_description": "## SHOP by LOOK  Compartilhando as produções, apostas e escolhas, aqui o nosso olhar sobre as peças e como usá-las em nossas casas"
}